dtoolcore/__init__.py
dtoolcore/compare.py
dtoolcore/filehasher.py
dtoolcore/storagebroker.py
dtoolcore/utils.py
dtoolcore/version.py
dtoolcore-3.19.0.dist-info/LICENSE.rst
dtoolcore-3.19.0.dist-info/METADATA
dtoolcore-3.19.0.dist-info/WHEEL
dtoolcore-3.19.0.dist-info/entry_points.txt
dtoolcore-3.19.0.dist-info/top_level.txt
dtoolcore-3.19.0.dist-info/RECORD
