Metadata-Version: 2.1
Name: dtoolcore
Version: 3.19.0
Summary: Core API for managing (scientific) data
Author-email: Tjelvar Olsson <tjelvar.olsson@gmail.com>
Project-URL: Documentation, https://dtoolcore.readthedocs.io
Project-URL: Repository, https://github.com/jic-dtool/dtoolcore
Project-URL: Changelog, https://github.com/jic-dtool/dtoolcore/blob/master/CHANGELOG.rst
License-File: LICENSE.rst
Requires-Dist: setuptools
Provides-Extra: test
Requires-Dist: pytest; extra == "test"
Requires-Dist: pytest-cov; extra == "test"
Requires-Dist: pytz; extra == "test"
Provides-Extra: docs
Requires-Dist: sphinx; extra == "docs"
Requires-Dist: sphinx_rtd_theme; extra == "docs"
